.dockerignore
.gitignore
CHANGES.txt
Dockerfile
LICENSE
README.rst
requirements.txt
setup.py
tox.ini
src/jira_exporter/__init__.py
src/jira_exporter/exporter.py
src/jira_exporter.egg-info/PKG-INFO
src/jira_exporter.egg-info/SOURCES.txt
src/jira_exporter.egg-info/dependency_links.txt
src/jira_exporter.egg-info/entry_points.txt
src/jira_exporter.egg-info/not-zip-safe
src/jira_exporter.egg-info/requires.txt
src/jira_exporter.egg-info/top_level.txt